keycloak_auth_policy/__init__.py
keycloak_auth_policy/policy.py
pyramid_keycloak-0.0.13.dist-info/LICENSE
pyramid_keycloak-0.0.13.dist-info/METADATA
pyramid_keycloak-0.0.13.dist-info/WHEEL
pyramid_keycloak-0.0.13.dist-info/top_level.txt
pyramid_keycloak-0.0.13.dist-info/RECORD
