Metadata-Version: 2.1
Name: pyramid-keycloak
Version: 0.0.13
Summary: Keycloak based authentication policy for Pyramid
Home-page: https://github.com/watsta/keycloak_pyramid
Author: Krisztian Toth
Author-email: tkrisztiana@gmail.com
License: UNKNOWN
Platform: UNKNOWN
Classifier: Programming Language :: Python :: 3
Classifier: Operating System :: OS Independent
Requires-Dist: pyramid (<2.0,>1.0)
Requires-Dist: python-keycloak (<1.0)
